{
  "version": 1,
  "skills": {
    "apify": {
      "version": "1.0.3",
      "installedAt": 1776816737744
    },
    "google-analytics": {
      "version": "1.0.10",
      "installedAt": 1776816740058
    },
    "google-search-console": {
      "version": "1.0.5",
      "installedAt": 1776816742307
    },
    "google-ads": {
      "version": "1.1.0",
      "installedAt": 1776816744666
    },
    "meta-ads": {
      "version": "1.0.0",
      "installedAt": 1776816746706
    },
    "apollo": {
      "version": "1.0.0",
      "installedAt": 1776816749168
    },
    "native-google-analytics": {
      "version": "0.1.1",
      "installedAt": 1776816751730
    },
    "gsc": {
      "version": "1.2.2",
      "installedAt": 1776816754112
    },
    "metricool": {
      "version": "1.0.0",
      "installedAt": 1776816757052
    },
    "larry": {
      "version": "1.0.0",
      "installedAt": 1776816760283
    },
    "nano-banana-pro": {
      "version": "1.0.1",
      "installedAt": 1776816761886
    }
  }
}
