{
  "$schema": "../../_system/sources.schema.json",
  "slug": "hospital-capilar",
  "name": "Hospital Capilar",
  "guild_id": "1475635138108063746",
  "language": "es",
  "channels": {
    "general": "1475635138988609678",
    "onboarding": "1476491108421730334",
    "brand": "1475638249107095866",
    "campaigns": "1475638251485401171",
    "partners": "1475638255641952386",
    "prospecting": "1475638257088860244",
    "content": "1475638259425087629",
    "paid-ads": "1475638261819900146",
    "web": "1475638263720181841",
    "creatives": "1475638268015022284",
    "research": "1475638269109862463",
    "intelligence": "1475638253154603170",
    "learning": "1475638272523763834",
    "soporte": "1475638273501040681"
  },
  "crons": {
    "daily_pulse": {
      "enabled": true,
      "schedule": "0 9 * * 1-5",
      "tz": "Europe/Madrid",
      "publish_channel": "intelligence",
      "read_channels": ["general", "brand", "campaigns", "content", "intelligence", "onboarding", "soporte", "research", "paid-ads"]
    },
    "meeting_intelligence": {
      "enabled": true,
      "schedule": "0 18 * * 1-5",
      "tz": "Europe/Madrid",
      "publish_channel": "intelligence",
      "google_drive_folder_id": "17FpwSgL-XLAqaaH5-UccpADHkCFRcCHY"
    },
    "weekly_synthesis": {
      "enabled": true,
      "schedule": "0 10 * * 1",
      "tz": "Europe/Madrid",
      "publish_channel": "learning"
    },
    "thief_marketer": {
      "enabled": false,
      "schedule": "0 8 * * 3",
      "tz": "Europe/Madrid",
      "publish_channel": "intelligence"
    }
  }
}
