{
  "cronName": "Daily Pulse — Growth4U",
  "slug": "growth4u",
  "date": "2026-04-21",
  "runAtMs": 1776756484782,
  "status": "ok",
  "content": "Martes 21 abril — día 16 sin citas. Meta Ads: 1 lead ayer (vs media 2.7/día) — peor día de la semana. CTR 0.67% < media 0.83%, CPC €3.82 > media €3.07. 4 contactos nuevos en GHL (óscar, kiko requena, jose vía lead magnet + daniel Facebook), 0 citas. Servidor Discord con 0 mensajes humanos. La crisis de conversión se mantiene: se generan leads pero no llegan a booking. ACCIÓN CRÍTICA: аудит del flujo booking GHL."
}