{
  "cronName": "Performance Analysis — Growth4U",
  "slug": "growth4u",
  "date": "2026-05-11",
  "runAtMs": 1747000800000,
  "status": "ok",
  "content": "W19 (May 5-11). Health Score: 42/100 (↑+5 vs W18=37). NSM: 0 meetings esta semana (vs 4 W18) — on_track: false. ANOMALÍAS: 🔴 Appointments=0 toda la semana (25 contactos, 0 reuniones — Lead→Meeting roto a 0%). 🟡 CPL €45.22 (-35% vs W18 pero 2.5x target). 🟢 CTR recovery 1.57% (+171% vs W18 0.58%) — primera recuperación sostenida en 7 semanas. 🟡 SEO position ~10.5 (sin recuperación). RECOMENDACIONES HIGH: (1) Diagnosticar GHL booking urgente — 0 meetings con 25 leads es fallo técnico o de proceso, (2) Investigar causa CTR recovery y capitalizar, (3) P01 Pixel deadline pasado — decidir instalar o reducir budget, (4) Lanzar P03 cold email esta semana — pipeline vacío sin excusa."
}
