{
  "cronName": "Weekly Synthesis — Growth4U",
  "slug": "growth4u",
  "date": "2026-05-11",
  "runAtMs": 1747000440000,
  "status": "ok",
  "content": "## Síntesis Semanal W19 — Growth4U (5–11 mayo 2026)\n\n### 🔴 HALLAZGO PRINCIPAL\nParadoja W19 confirmada: mejores métricas de captación en semanas pero 0 meetings. CTR +3x, CPL -35%, contacts +150% — pero 0 appointments en 7 días. El funnel lead→cita lleva 5 semanas roto de forma estructural. Un fix de 30 minutos en GHL puede desbloquear 10 meetings/semana.\n\n### Patrones Confirmados\n1. Gap lead→cita: semana 5 crónica. 33 leads con 'llamada-agendada', 0 citas. Conversión cayó de 40% (W18) a 0% (W19).\n2. Paradoja CTR/CPL vs pipeline: CTR 0.52%→1.57% (+3x), CPL €70→€45 (-35%), contacts +150%. Pero 0 meetings.\n3. Health Score: 22 (mínimo) → 37 → 42. Primera recuperación sostenida en 3 semanas. Impulsada por paid, no pipeline.\n4. Meta Ads alta volatilidad: CPC osciló €2.64→€4.04 en 48h. Impresiones -73% el viernes 8 mayo.\n5. CTR subió sin Pixel activo — algo cambió en Meta (algoritmo/audiencia), investigar.\n6. P01 Pixel+CAPI: semana 8+ sin completar. Deadline 11-May incumplido.\n7. 0 mensajes humanos Discord: semana 10+.\n\n### Leads Clave\n- Frank Nava (Rentakia, PropTech): muy interesado Trust Engine, objeción 9K€, follow-up con socio Víctor pendiente.\n- Aarón Sanromán: plan LinkedIn 3 meses, 20K seguidores target.\n- Jordi Teixido de Haro: developer + FB Ads, call 11/05.\n- Eustacio Cabrera (MERGE Madrid, Web3): seguimiento activo.\n- Luis Ayuso (Infonite, Open Banking): seguimiento-2 activo.\n\n### Señales de Mercado\n- GEO/Zero-Click: 25-50% B2B buyers usan AI para research.\n- MiCA deadline julio 2026: compliance-as-moat.\n- AI Agents: 88% dice usarlo, solo 6% operativo.\n\n### Acciones P0\n1. Diagnosticar y fijar booking GHL (30 min que desbloquean todo) — Alfonso/Philippe\n2. Seguimiento Frank Nava con propuesta fraccionada — Alfonso/Martín\n3. Instalar Pixel+CAPI (P01 — 8+ semanas pendiente) — Philippe\n4. Investigar anomalía impresiones -73% + spike CPC — Philippe\n5. Fix Slack bot scope chat:write — Cervantes\n6. Activar P03 cold email (dependencia 100% Meta = riesgo sistémico) — equipo"
}
