{
  "module": "gap-analysis",
  "version": 1,
  "created_at": "2026-04-07T13:18:00Z",
  "updated_at": "2026-04-07T13:18:00Z",
  "status": "completed",
  "data": {
    "execution_summary": {
      "geo_input": "geo-analysis.json — 18 runs, 89 citations",
      "serp_input": "serp-analysis.json — 42 keywords, partial data",
      "competitor_domains": ["producthackers.com", "agenciasnowball.com", "thegrowthacker.com", "isocialweb.agency", "flake-agency.com", "teamlewis.com"],
      "gap_modes_executed": ["presence", "density", "type"],
      "total_gaps_identified": 18
    },
    "gap_modes": {
      "presence_gaps": {
        "description": "Client NOT present but competitors ARE present",
        "count": 6,
        "gaps": [
          {
            "gap_id": "gap-pres-001",
            "gap_type": "presence",
            "niche": "n2",
            "subnicho": "n2-s1",
            "domain": "cnmv.es",
            "domain_type": "editorial_authority",
            "specific_url": "https://www.cnmv.es/DocPortal/Publicaciones/Fichas/GR13_Publicidad_financiera.pdf",
            "url_title": "CNMV Ficha GR13 - Publicidad de productos financieros",
            "gap_source": "geo_only",
            "competitors_present": [],
            "competitor_count": 0,
            "client_present": false,
            "opportunity_score": 95,
            "suggested_action": "Enviary nota de prensa o guest post sobre marketing CNMV-compliant. La CNMV no recomienda agencias específicas — pero los despachos que saben de marketing SÍ podrían citar a Growth4U.",
            "suggested_collaboration_type": "artículo_en_media",
            "per_subnicho": ["n2-s1", "n2-s2"]
          },
          {
            "gap_id": "gap-pres-002",
            "gap_type": "presence",
            "niche": "n2",
            "subnicho": "n2-s1",
            "domain": "finreg360.com",
            "domain_type": "editorial_authority",
            "specific_url": "https://finreg360.com",
            "url_title": "FinReg360 - expertise regulatorio fintech",
            "gap_source": "geo_only",
            "competitors_present": [],
            "competitor_count": 0,
            "client_present": false,
            "opportunity_score": 90,
            "suggested_action": "Contacto con FinReg360 para partnership o guest post sobre marketing compliance-friendly. FinReg360 es referente para compliance — una mención suya sobre marketing sería oro.",
            "suggested_collaboration_type": "asociacion",
            "per_subnicho": ["n2-s1", "n2-s2"]
          },
          {
            "gap_id": "gap-pres-003",
            "gap_type": "presence",
            "niche": "n4",
            "subnicho": "n4-s2",
            "domain": "reddit.com",
            "domain_type": "community",
            "specific_url": "https://reddit.com/r/emprendimiento",
            "url_title": "r/emprendimiento - forum discussion on agency experiences",
            "gap_source": "geo_only",
            "competitors_present": [],
            "competitor_count": 0,
            "client_present": false,
            "opportunity_score": 85,
            "suggested_action": "Responder genuinamente en hilos de founders quemados por agencias. NO vender — compartir framework y dejar que vean que existe Growth4U. Link solo si preguntan.",
            "suggested_collaboration_type": "community_presence",
            "per_subnicho": ["n4-s1", "n4-s2"]
          },
          {
            "gap_id": "gap-pres-004",
            "gap_type": "presence",
            "niche": "n1",
            "subnicho": "n1-s1",
            "domain": "isoccialweb.agency",
            "domain_type": "portal_sectorial",
            "specific_url": "https://isocialweb.agency/mejores-agencias-growth-hacking/",
            "url_title": "Top 10 Mejores Agencias Growth Hacking España",
            "gap_source": "serp_only",
            "competitors_present": ["Product Hackers", "Flat 101", "TheGrowtHacker"],
            "competitor_count": 3,
            "client_present": false,
            "opportunity_score": 75,
            "suggested_action": "Solicitar inclusión en el ranking de iSocialWeb. Son el referente en España para rankings de agencias. Si Growth4U aparece, captura tráfico de alta intención.",
            "suggested_collaboration_type": "inclusion_en_ranking",
            "per_subnicho": ["n1-s1", "n1-s2"]
          },
          {
            "gap_id": "gap-pres-005",
            "gap_type": "presence",
            "niche": "n1",
            "subnicho": "n1-s1",
            "domain": "flake-agency.com",
            "domain_type": "competitor",
            "specific_url": "https://flake-agency.com/marketing-fintech/",
            "url_title": "Flake Agency - Agencia Marketing Fintech España",
            "gap_source": "serp_only",
            "competitors_present": ["Flake Agency"],
            "competitor_count": 1,
            "client_present": false,
            "opportunity_score": 60,
            "suggested_action": "Crear contenido comparativo 'Flake Agency vs Growth4U' para diferenciarse en SEO. O crear contenido sobre por qué una agencia fintech especializada importa más que una generalista.",
            "suggested_collaboration_type": "comparativa",
            "per_subnicho": ["n2-s1"]
          },
          {
            "gap_id": "gap-pres-006",
            "gap_type": "presence",
            "niche": "n1",
            "subnicho": "n1-s1",
            "domain": "producthackers.com",
            "domain_type": "competitor",
            "specific_url": "https://producthackers.com",
            "url_title": "Product Hackers - Full Business Growth",
            "gap_source": "serp_only",
            "competitors_present": ["Product Hackers"],
            "competitor_count": 1,
            "client_present": false,
            "opportunity_score": 50,
            "suggested_action": "Product Hackers Go! Slack: ser activo en hilos sobre growth. Responder con frameworks accionables. No vender — compartir valor. Earn trust antes de pitch.",
            "suggested_collaboration_type": "community",
            "per_subnicho": ["n1-s1", "n1-s5"]
          }
        ]
      },
      "density_gaps": {
        "description": "Client present but competitors have 3x more mentions in same domain",
        "count": 4,
        "gaps": [
          {
            "gap_id": "gap-dens-001",
            "gap_type": "density",
            "niche": "n1",
            "subnicho": "n1-s1",
            "domain": "growth4u.io",
            "domain_type": "own",
            "specific_url": "https://growth4u.io/blog/",
            "url_title": "Blog Growth4U",
            "gap_source": "geo_only",
            "client_mentions": 8,
            "max_competitor_mentions": 4,
            "density_ratio": "2x",
            "opportunity_score": 70,
            "suggested_action": "Duplicar número de artículos blog para competir con Product Hackers que tiene 100+ artículos. Crear 5+ artículos nuevos sobre growth systems y comparativas.",
            "suggested_collaboration_type": "content_expansion",
            "per_subnicho": ["n1-s1", "n1-s2", "n1-s3"]
          },
          {
            "gap_id": "gap-dens-002",
            "gap_type": "density",
            "niche": "n1",
            "subnicho": "n1-s1",
            "domain": "cincoillas.elpais.com",
            "domain_type": "media",
            "specific_url": "https://cincodias.elpais.com/cincodias/2020/01/06/companias/1578341441_525921.html",
            "url_title": "Artículo Bnext Cinco Días - caso Alfonso",
            "gap_source": "geo_only",
            "client_mentions": 2,
            "max_competitor_mentions": 0,
            "density_ratio": "N/A (no competitor)",
            "opportunity_score": 40,
            "suggested_action": "Alfonso ya tiene presencia en Cinco Días. Necesita UN artículo de PR sobre Growth4U como empresa, no solo sobre sus roles previos.",
            "suggested_collaboration_type": "pr",
            "per_subnicho": ["n5-s3"]
          },
          {
            "gap_id": "gap-dens-003",
            "gap_type": "density",
            "niche": "n2",
            "subnicho": "n2-s1",
            "domain": "trustpilot.com",
            "domain_type": "review",
            "specific_url": "https://trustpilot.com/review/growth4u.io",
            "url_title": "Growth4U Trustpilot - 1 review 3.5/5",
            "gap_source": "geo_only",
            "client_mentions": 2,
            "max_competitor_mentions": 0,
            "density_ratio": "N/A (no competitor has reviews either)",
            "opportunity_score": 80,
            "suggested_action": "Pedir reviews a clientes Trust Engine actuales. Primeros 3-5 clientes = social proof crítica. Con 5+ reviews de 4+, Growth4U supera a todos los competidores que tienen 0.",
            "suggested_collaboration_type": "reviews",
            "per_subnicho": ["n5-s2"]
          },
          {
            "gap_id": "gap-dens-004",
            "gap_type": "density",
            "niche": "n1",
            "subnicho": "n1-s1",
            "domain": "ajtapia.com",
            "domain_type": "authority",
            "specific_url": "https://ajtapia.com",
            "url_title": "Javier Tapia - lawyer fintech expertise",
            "gap_source": "geo_only",
            "client_mentions": 0,
            "max_competitor_mentions": 0,
            "density_ratio": "WHITE SPACE",
            "opportunity_score": 88,
            "suggested_action": "Contactar a Javier Tapia para guest post sobre marketing CNMV-compliant. Es ajeno al sector growth — una colaboración Cruzada les aporta contenido valioso a sus lectores.",
            "suggested_collaboration_type": "guest_post",
            "per_subnicho": ["n2-s1", "n2-s2"]
          }
        ]
      },
      "type_gaps": {
        "description": "Client has list mentions but competitors have dedicated articles",
        "count": 5,
        "gaps": [
          {
            "gap_id": "gap-type-001",
            "gap_type": "type",
            "niche": "n1",
            "subnicho": "n1-s1",
            "domain": "producthackers.com",
            "domain_type": "competitor",
            "specific_url": "https://producthackers.com",
            "url_title": "Product Hackers - Full Business Growth",
            "gap_source": "serp_only",
            "client_mention_type": "none",
            "competitor_mention_type": "dedicated_article",
            "gap_description": "Product Hackers has dedicated ranking pages and comparison content. Growth4U has 0 presence.",
            "opportunity_score": 75,
            "suggested_action": "Crear landing page dedicada a comparativa 'Growth4U vs Product Hackers' para captar tráfico de búsqueda comparativo.",
            "suggested_collaboration_type": "content_comparativo",
            "per_subnicho": ["n1-s1"]
          },
          {
            "gap_id": "gap-type-002",
            "gap_type": "type",
            "niche": "n2",
            "subnicho": "n2-s1",
            "domain": "fundssociety.com",
            "domain_type": "media",
            "specific_url": "https://fundssociety.com",
            "url_title": "Fund Society - fintech news",
            "gap_source": "geo_only",
            "client_mention_type": "none",
            "competitor_mention_type": "none",
            "gap_description": "CNMV cited fundssociety.com for influencer marketing guidance. Growth4U has 0 presence. This is a media outlet that covers fintech news — perfect for PR.",
            "opportunity_score": 82,
            "suggested_action": "Enviar nota de prensa sobre 'Estado del marketing fintech en España' o 'Guía CNMV para marketers'. Fundssociety cubre estas noticias.",
            "suggested_collaboration_type": "nota_prensa",
            "per_subnicho": ["n2-s1", "n2-s2"]
          },
          {
            "gap_id": "gap-type-003",
            "gap_type": "type",
            "niche": "n4",
            "subnicho": "n4-s2",
            "domain": "malt.es",
            "domain_type": "directory",
            "specific_url": "https://malt.es/profile/daniruizalba",
            "url_title": "Dani Ruiz (TheGrowtHacker) profile on Malt",
            "gap_source": "serp_only",
            "client_mention_type": "none",
            "competitor_mention_type": "profile",
            "gap_description": "TheGrowtHacker has a Malt profile with reviews. Growth4U does not. Malt is a key directory for freelance/agency discovery in Spain.",
            "opportunity_score": 70,
            "suggested_action": "Crear perfil de Alfonso y Growth4U en Malt con portfolio y casos. Es gratis y captura tráfico de founders buscando consultores.",
            "suggested_collaboration_type": "perfil_en_directorio",
            "per_subnicho": ["n4-s1", "n4-s2"]
          },
          {
            "gap_id": "gap-type-004",
            "gap_type": "type",
            "niche": "n4",
            "subnicho": "n4-s1",
            "domain": "osi.es",
            "domain_type": "authority",
            "specific_url": "https://www.osi.es/es/actualidad/avisos",
            "url_title": "OSI - Agencia de Seguridad",
            "gap_source": "geo_only",
            "client_mention_type": "none",
            "competitor_mention_type": "none",
            "gap_description": "OSI (Oficina de Seguridad del Internauta) cited for 'agency scam' queries. Growth4U has no presence. OSI doesn't cover agencies specifically — but it's cited in the same conversation.",
            "opportunity_score": 45,
            "suggested_action": "Crear contenido sobre cómo verificar agencias (sin nombrar a OSI). No hay oportunidad de colaboración directa.",
            "suggested_collaboration_type": "content",
            "per_subnicho": ["n4-s2"]
          },
          {
            "gap_id": "gap-type-005",
            "gap_type": "type",
            "niche": "n5",
            "subnicho": "n5-s1",
            "domain": "elreferente.es",
            "domain_type": "media",
            "specific_url": "https://elreferente.es",
            "url_title": "El Referente - startup/fintech media",
            "gap_source": "geo_only",
            "client_mention_type": "none",
            "competitor_mention_type": "none",
            "gap_description": "El Referente covers fintech news and startup ecosystem. Growth4U should be featured there. Alfonso's background (Bnext, Bit2Me) is exactly the type of story El Referente covers.",
            "opportunity_score": 78,
            "suggested_action": "Enviar nota de prensa o proponer entrevista con Alfonso sobre 'Cómo hacer marketing fintech sin arriesgar la licencia'. El Referente es medio especializado en ecosistemas innovadores.",
            "suggested_collaboration_type": "entrevista",
            "per_subnicho": ["n2-s1", "n5-s3"]
          }
        ]
      }
    },
    "composite_scoring": {
      "formula": "score = (GEO_citations × 2) + (SERP_appearances × 1.5) + (num_AI_providers × 3) + type_bonus",
      "type_bonus_rules": {
        "geo_only": 15,
        "serp_only": 10,
        "geo_plus_serp": 25
      },
      "top_10_gaps_by_score": [
        { "gap_id": "gap-pres-001", "domain": "cnmv.es", "geo": 4, "serp": 0, "score": 23, "type_bonus": 15 },
        { "gap_id": "gap-pres-002", "domain": "finreg360.com", "geo": 2, "serp": 0, "score": 19, "type_bonus": 15 },
        { "gap_id": "gap-pres-003", "domain": "reddit.com", "geo": 1, "serp": 0, "score": 17, "type_bonus": 15 },
        { "gap_id": "gap-type-002", "domain": "fundssociety.com", "geo": 1, "serp": 0, "score": 17, "type_bonus": 15 },
        { "gap_id": "gap-pres-004", "domain": "isoccialweb.agency", "geo": 0, "serp": 1, "score": 16.5, "type_bonus": 10 },
        { "gap_id": "gap-type-005", "domain": "elreferente.es", "geo": 1, "serp": 0, "score": 17, "type_bonus": 15 },
        { "gap_id": "gap-pres-006", "domain": "producthackers.com", "geo": 0, "serp": 1, "score": 16.5, "type_bonus": 10 },
        { "gap_id": "gap-pres-005", "domain": "flake-agency.com", "geo": 0, "serp": 1, "score": 16.5, "type_bonus": 10 },
        { "gap_id": "gap-dens-003", "domain": "trustpilot.com", "geo": 2, "serp": 0, "score": 19, "type_bonus": 15 },
        { "gap_id": "gap-dens-004", "domain": "ajtapia.com", "geo": 0, "serp": 0, "score": 0, "type_bonus": 15 }
      ]
    },
    "domain_taxonomy": {
      "editorial_authority": ["cnmv.es", "finreg360.com", "ajtapia.com"],
      "media": ["cincoill as.elpais.com", "fundssociety.com", "elreferente.es", "elasesorfinanciero.com"],
      "portal_sectorial": ["flake-agency.com", "producthackers.com"],
      "competitor": ["producthackers.com", "flake-agency.com", "thegrowthacker.com", "agenciasnowball.com", "isoccialweb.agency"],
      "directory": ["trustpilot.com", "malt.es", "g2.com", "capterra.com"],
      "community": ["reddit.com", "reddit.com/r/saas", "reddit.com/r/emprendimiento"],
      "review": ["trustpilot.com"]
    },
    "excluded_domains": {
      "competitors": ["producthackers.com", "flake-agency.com", "thegrowthacker.com", "agenciasnowball.com", "isoccialweb.agency"],
      "wrong_market": ["growth4u.org (brand confusion)", "growth4u.cl", "growth4u.fr"]
    }
  },
  "metadata": {
    "duration_seconds": 120,
    "apis_called": [],
    "errors": [],
    "quality_gate_passed": true
  }
}
